[
  {
    "title": "U9jvxfxuM0wy2/X3vPoDCQJzfnb1wdKCIuL26HD6TH4=",
    "id_tag": "1444748613",
    "total": 1000,
    "rank": 0,
    "page": 56,
    "has_limit": false
  },
  {
    "title": "U9jvxfxuM0wy2/X3vPoDCdU2zsEB+ATsGDe8I1o5otY=",
    "id_tag": "1444748614",
    "total": 1000,
    "rank": 0,
    "page": 56,
    "has_limit": false
  },
  {
    "title": "U9jvxfxuM0wy2/X3vPoDCWg8/CxDl1DkC9bA9yf30Hs=",
    "id_tag": "1444748615",
    "total": 1000,
    "rank": 0,
    "page": 56,
    "has_limit": false
  },
  {
    "title": "U9jvxfxuM0wy2/X3vPoDCTrHYA/Cc6ePCcy/Wud/YNY=",
    "id_tag": "1444748616",
    "total": 1000,
    "rank": 0,
    "page": 57,
    "has_limit": false
  },
  {
    "title": "U9jvxfxuM0wy2/X3vPoDCV3GEY4uIL7nM31vFGBhets=",
    "id_tag": "1444748617",
    "total": 337,
    "rank": 0,
    "page": 59,
    "has_limit": false
  }
]